manchester_code/__init__.py
manchester_code-1.1.0.dist-info/COPYING
manchester_code-1.1.0.dist-info/METADATA
manchester_code-1.1.0.dist-info/WHEEL
manchester_code-1.1.0.dist-info/top_level.txt
manchester_code-1.1.0.dist-info/RECORD
