Metadata-Version: 2.1
Name: manchester-code
Version: 1.1.0
Summary: Python library to encode & decode data as Manchester code
Home-page: https://github.com/fphammerle/python-manchester-code
Author: Fabian Peter Hammerle
Author-email: fabian+python-manchester-code@hammerle.me
License: GPLv3+
Project-URL: Changelog, https://github.com/fphammerle/python-manchester-code/blob/master/CHANGELOG.md
Keywords: phase encoding,radio frequency,telecommunication,transmission
Platform: UNKNOWN
Classifier: Development Status :: 3 - Alpha
Classifier: Intended Audience :: Developers
Classifier: License :: OSI Approved :: GNU General Public License v3 or later (GPLv3+)
Classifier: Operating System :: POSIX :: Linux
Classifier: Programming Language :: Python :: 3.5
Classifier: Programming Language :: Python :: 3.6
Classifier: Programming Language :: Python :: 3.7
Classifier: Programming Language :: Python :: 3.8
Classifier: Topic :: Communications
